[
  {
    "id": 1,
    "date": "2025-05-26",
    "title": "Chilling report gives Europe ‘two years’",
    "content": "A startling report has warned of a new “significant military challenge” facing Europe which could come “as early as 2027”.",
    "category": "World"
  },
  {
    "id": 2,
    "date": "2025-05-19",
    "title": "EU to give in on key issue for mega deal",
    "content": "With Europe getting hit hard by Donald Trump’s tariffs, the EU is looking to strike a deal with Australia.",
    "category": "World"
  },
  {
    "id": 3,
    "date": "2025-05-18",
    "title": "Vance’s stunning act at Pope’s mass",
    "content": "US vice-president JD Vance has raised eyebrows with a surprising act at Pope Leo XIV’s papal mass in Rome.",
    "category": "World"
  },
  {
    "id": 4,
    "date": "2024-10-25",
    "title": "Truth about flying budget airline long haul",
    "content": "I recently spent 24 hours in the air on a low-cost airline – and you can do it too.",
    "category": "Travel"
  },
  {
    "id": 5,
    "date": "2025-05-26",
    "title": "Adelaide locals revolt over Tesla plan",
    "content": "Adelaide residents have erupted over a proposal to build a Tesla factory in the city’s southern suburbs.",
    "category": "Technology"
  },
  {
    "id": 6,
    "date": "2025-05-24",
    "title": "ABC host tricked by reporter’s ‘convincing’ deepfake",
    "content": "ABC host Sarah Ferguson struggled to recognise her own colleague from his AI-generated doppelganger live on air.",
    "category": "Technology"
  },
  {
    "id": 7,
    "date": "2025-05-24",
    "title": "Aussie rejected at US border, deported",
    "content": "A young Aussie who was rejected at the US border and sent back on the first flight home",
    "category": "Travel"
  },
  {
    "id": 8,
    "date": "2025-05-26",
    "title": "‘Unacceptable’: Albo blasts Israel aid block",
    "content": "Anthony Albanese has blasted Israel for not allowing more aid to flow freely into Gaza",
    "category": "World"
  },
  {
    "id": 9,
    "date": "2025-05-12",
    "title": "Countdown to Aussie space dream begins",
    "content": "The countdown has begun for an Aussie company’s dream to lift-off into space and begin competing with Elon Musk’s SpaceX.",
    "category": "Technology"
  },
  {
    "id": 10,
    "date": "2024-08-07",
    "title": "Aussie star shocked by sweet Bali act",
    "content": "An Aussie TikTok star said she ‘almost cried’ when this happened to her at a restaurant in Bali.",
    "category": "Travel"
  }
]